naver_web/__init__.py
naver_web/connect.py
naver_web/proxy.py
test/__init__.py
test/naver_hash.py
test/naver_salt.py
naver_web-0.0.1.post8.dist-info/METADATA
naver_web-0.0.1.post8.dist-info/WHEEL
naver_web-0.0.1.post8.dist-info/top_level.txt
naver_web-0.0.1.post8.dist-info/RECORD
