Metadata-Version: 2.1
Name: naver-web
Version: 0.0.1.post8
Summary: A Web Ancestor Library
Home-page: https://github.com/jacr6/naver-web
Author: Jose Cuevas
Author-email: jose.cuevas.cv@gmail.com
License: UNKNOWN
Platform: UNKNOWN
Classifier: Programming Language :: Python :: 3
Classifier: License :: OSI Approved :: MIT License
Classifier: Operating System :: OS Independent
Requires-Dist: Flask
Requires-Dist: flask-restx
Requires-Dist: cryptography
